eyw/__init__.py
eyw-0.0.3.dist-info/METADATA
eyw-0.0.3.dist-info/WHEEL
eyw-0.0.3.dist-info/licenses/LICENSE.txt
eyw-0.0.3.dist-info/RECORD
