Metadata-Version: 2.4
Name: eyw
Version: 0.0.3
Summary: Useful functions that are intended to be used with the Engineer Your World Computing Curriculum
Project-URL: Homepage, https://engineeryourworld.utexas.edu
Project-URL: Issues, https://engineeryourworld.utexas.edu
Author-email: Engineer Your World <engineeryourworld@austin.utexas.edu>, Kyle Fricke <kyle.fricke@austinlutexas.edu>
License-File: LICENSE.txt
Classifier: License :: OSI Approved :: GNU General Public License v3 (GPLv3)
Classifier: Operating System :: OS Independent
Classifier: Programming Language :: Python :: 3
Requires-Python: >=3.0
